{
    "ptr_offset": null,
    "content": {
        "pallete": [
            {
                "offset": 0,
                "size": 1024
            }
        ],
        "pixel": [
            {
                "format": "-pspindex8",
                "offset": 6144,
                "size": 6144,
                "width": 512,
                "height": 272,
                "chunk": 4,
                "chunk_offset": [
                    32,
                    7600,
                    12576,
                    20688,
                    24720
                ],
                "gzip_csizes": [
                    7568,
                    4976,
                    8112,
                    4032
                ],
                "gzip_dsizes": [
                    34816,
                    34816,
                    34816,
                    34816
                ]
            }
        ]
    }
}